espoofer/__init__.py
espoofer/config.py
espoofer/espoofer.py
espoofer/exploits_builder.py
espoofer/testcases.py
espoofer/common/__init__.py
espoofer/common/common.py
espoofer/common/mail_sender.py
espoofer/dkim/__init__.py
espoofer/dkim/__main__.py
espoofer/dkim/arcsign.py
espoofer/dkim/arcverify.py
espoofer/dkim/asn1.py
espoofer/dkim/canonicalization.py
espoofer/dkim/crypto.py
espoofer/dkim/dkimsign.py
espoofer/dkim/dkimverify.py
espoofer/dkim/dknewkey.py
espoofer/dkim/dnsplug.py
espoofer/dkim/util.py
espoofer-0.9.1.dist-info/METADATA
espoofer-0.9.1.dist-info/WHEEL
espoofer-0.9.1.dist-info/entry_points.txt
espoofer-0.9.1.dist-info/top_level.txt
espoofer-0.9.1.dist-info/RECORD
