Metadata-Version: 2.1
Name: espoofer
Version: 0.9.1
Summary: An email spoofing testing tool that aims to bypass SPF/DKIM/DMARC and forge DKIM signatures
Home-page: http://github.com/chenjj/espoofer
Author: Jianjun Chen
Author-email: whucjj@hotmail.com
License: MIT
Project-URL: Bug Reports, https://github.com/chenjj/espoofer/issues
Project-URL: Source, https://github.com/chenjj/espoofer/
Platform: UNKNOWN
Classifier: Development Status :: 4 - Beta
Classifier: License :: OSI Approved :: MIT License
Classifier: Natural Language :: English
Classifier: Operating System :: OS Independent
Classifier: Programming Language :: Python
Classifier: Environment :: Console
Classifier: Topic :: Security
Requires-Python: >=3.5, <4
Requires-Dist: colorama
Requires-Dist: simplejson
Requires-Dist: argparse
Requires-Dist: dnspython
